ariane_lib/__init__.py
ariane_lib/enums.py
ariane_lib/key_map.py
ariane_lib/parser.py
ariane_lib/section.py
ariane_lib/shot.py
ariane_lib/type_utils.py
ariane_lib/commands/__init__.py
ariane_lib/commands/convert.py
ariane_lib/commands/correct.py
ariane_lib/commands/main.py
ariane_lib-0.0.3.dist-info/entry_points.txt
ariane_lib-0.0.3.dist-info/licenses/LICENSE
ariane_lib-0.0.3.dist-info/WHEEL
ariane_lib-0.0.3.dist-info/METADATA
ariane_lib-0.0.3.dist-info/RECORD
