Metadata-Version: 2.4
Name: ariane_lib
Version: 0.0.3
Summary: A library to read Ariane Line Survey Software files
Keywords: cave,survey,karst
Author-email: Jonathan Dekhtiar <jonathan@dekhtiar.com>
Maintainer-email: Jonathan Dekhtiar <jonathan@dekhtiar.com>
Requires-Python: >=3.10
Classifier: Development Status :: 3 - Alpha
Classifier: Intended Audience :: Developers
Classifier: Intended Audience :: Science/Research
Classifier: Intended Audience :: Information Technology
Classifier: Topic :: Software Development :: Build Tools
Classifier: Topic :: Scientific/Engineering
Classifier: Topic :: Software Development :: Libraries
Classifier: Topic :: Utilities
Classifier: License :: OSI Approved :: Apache Software License
Classifier: Operating System :: OS Independent
Classifier: Programming Language :: Python :: 3
Classifier: Programming Language :: Python :: 3 :: Only
License-File: LICENSE
Requires-Dist: defusedxml>=0.7,<0.8
Requires-Dist: dicttoxml2>=2.1,<2.2
Requires-Dist: orjson>=3.10,<3.12
Requires-Dist: xmltodict>=1.0,<1.1
Requires-Dist: pytest>=8.0.0,<9.0.0 ; extra == "test"
Requires-Dist: pytest-cov>=5.0.0,<8.0.0 ; extra == "test"
Requires-Dist: pytest-dotenv>=0.5.0,<1.0.0 ; extra == "test"
Requires-Dist: pytest-env>=1.1.3,<2.0.0 ; extra == "test"
Requires-Dist: pytest-runner>=6.0.0,<7.0.0 ; extra == "test"
Requires-Dist: pytest-ordering>=0.6,<1.0.0 ; extra == "test"
Requires-Dist: parameterized>=0.9.0,<0.10 ; extra == "test"
Project-URL: Bug Reports, https://github.com/OpenSpeleo/pytool_ariane_lib/issues
Project-URL: Homepage, https://pypi.org/project/ariane-lib/
Project-URL: Source, https://github.com/OpenSpeleo/pytool_ariane_lib
Provides-Extra: test
